TestAuto/__init__.py
TestAuto/management.py
TestAuto/api/__init__.py
TestAuto/core/__init__.py
TestAuto/core/baseapi.py
TestAuto/core/basetest.py
TestAuto/core/create_project.py
TestAuto/core/handle_path.py
TestAuto/utils/__init__.py
TestAuto-0.0.3.dist-info/METADATA
TestAuto-0.0.3.dist-info/WHEEL
TestAuto-0.0.3.dist-info/entry_points.txt
TestAuto-0.0.3.dist-info/top_level.txt
TestAuto-0.0.3.dist-info/RECORD
