Metadata-Version: 2.1
Name: TestAuto
Version: 0.0.3
Summary: UNKNOWN
Home-page: https://github.com/musen123/TestAuto
Author: MuSen
Author-email: musen_nmb@qq.com
License: UNKNOWN
Platform: UNKNOWN
Classifier: Programming Language :: Python :: 3
Requires-Python: >=3.6
Requires-Dist: Jinja2 (==2.10.1)
